lol_esp_api/__init__.py
lol_esp_api/lol_esports_api.py
lol_esp_api/apis/__init__.py
lol_esp_api/apis/eventsAPI.py
lol_esp_api/apis/leaguesAPI.py
lol_esp_api/apis/matchAPI.py
lol_esp_api/apis/supfunc.py
lol_esp_api/apis/teamsAPI.py
lol_esp_api-0.24.5.dist-info/LICENSE
lol_esp_api-0.24.5.dist-info/METADATA
lol_esp_api-0.24.5.dist-info/WHEEL
lol_esp_api-0.24.5.dist-info/top_level.txt
lol_esp_api-0.24.5.dist-info/RECORD
