Metadata-Version: 2.1
Name: lol-esp-api
Version: 0.24.5
Home-page: https://github.com/xMadKing/lol-esports-api
Author: xMadKing
Author-email: ahmad.kh.se@outlook.com
License: MIT
Keywords: League of legends,esports,lolesports,API
License-File: LICENSE
Requires-Dist: requests
